ft4222/__init__.py
ft4222/ft4222.cpython-311-aarch64-linux-gnu.so
ft4222/ft4222.pyi
ft4222/libft4222.so
ft4222/py.typed
ft4222/GPIO/__init__.py
ft4222/I2CMaster/__init__.py
ft4222/SPI/__init__.py
ft4222/SPIMaster/__init__.py
ft4222/SPISlave/__init__.py
ft4222-1.12.0.dist-info/LICENSE.txt
ft4222-1.12.0.dist-info/METADATA
ft4222-1.12.0.dist-info/WHEEL
ft4222-1.12.0.dist-info/top_level.txt
ft4222-1.12.0.dist-info/RECORD
