Metadata-Version: 2.2
Name: ft4222
Version: 1.12.0
Summary: Python wrapper around libFT4222.
Author-email: Bearsh <me@bearsh.org>
License: MIT
Project-URL: Homepage, https://gitlab.com/msrelectronics/python-ft4222
Keywords: ftdi,ft4222
Classifier: Development Status :: 5 - Production/Stable
Classifier: License :: OSI Approved :: MIT License
Classifier: License :: Other/Proprietary License
Classifier: Operating System :: Microsoft
Classifier: Operating System :: POSIX :: Linux
Classifier: Operating System :: MacOS :: MacOS X
Classifier: Typing :: Typed
Classifier: Programming Language :: Cython
Classifier: Programming Language :: Python
Classifier: Programming Language :: Python :: 3
Classifier: Programming Language :: Python :: 3.9
Classifier: Programming Language :: Python :: 3.10
Classifier: Programming Language :: Python :: 3.11
Classifier: Programming Language :: Python :: 3.12
Classifier: Programming Language :: Python :: 3.13
Classifier: Topic :: Communications
Requires-Python: >=3.9.0
License-File: LICENSE.txt
